odoo8_addon_l10n_br_zip_correios-8.0.1.0.0.99.dev20-py2.7-nspkg.pth
odoo8_addon_l10n_br_zip_correios-8.0.1.0.0.99.dev20.dist-info/METADATA
odoo8_addon_l10n_br_zip_correios-8.0.1.0.0.99.dev20.dist-info/RECORD
odoo8_addon_l10n_br_zip_correios-8.0.1.0.0.99.dev20.dist-info/WHEEL
odoo8_addon_l10n_br_zip_correios-8.0.1.0.0.99.dev20.dist-info/namespace_packages.txt
odoo8_addon_l10n_br_zip_correios-8.0.1.0.0.99.dev20.dist-info/top_level.txt
odoo_addons/l10n_br_zip_correios/README.rst
odoo_addons/l10n_br_zip_correios/__init__.py
odoo_addons/l10n_br_zip_correios/__openerp__.py
odoo_addons/l10n_br_zip_correios/i18n/pt_BR.po
odoo_addons/l10n_br_zip_correios/models/__init__.py
odoo_addons/l10n_br_zip_correios/models/l10n_br_zip.py
odoo_addons/l10n_br_zip_correios/models/webservice_client.py
odoo_addons/l10n_br_zip_correios/static/description/icon.png
odoo_addons/l10n_br_zip_correios/tests/__init__.py
odoo_addons/l10n_br_zip_correios/tests/test_webservice_client.py
